{
 "cells": [
  {
   "cell_type": "code",
   "execution_count": 2,
   "id": "4b9c90f5-1b01-42c7-8492-cce76cfce32b",
   "metadata": {},
   "outputs": [],
   "source": [
    "import dis"
   ]
  },
  {
   "cell_type": "code",
   "execution_count": null,
   "id": "602b3d5e-707e-4c23-ae07-a80ef26707be",
   "metadata": {},
   "outputs": [],
   "source": [
    "dis.dis(\"1+1\")"
   ]
  },
  {
   "cell_type": "code",
   "execution_count": null,
   "id": "5eacc710-d02c-4690-a020-99b6b06d6d84",
   "metadata": {},
   "outputs": [],
   "source": [
    "def add_ones():\n",
    "    return 1 + 1\n",
    "\n",
    "dis.dis(add_ones)"
   ]
  },
  {
   "cell_type": "code",
   "execution_count": null,
   "id": "73c914aa-9fd3-4a58-a978-a958b6e3a7f4",
   "metadata": {},
   "outputs": [],
   "source": [
    "def add_two_numbers(a, b):\n",
    "    return a + b\n",
    "\n",
    "dis.dis(add_two_numbers)"
   ]
  },
  {
   "cell_type": "code",
   "execution_count": null,
   "id": "81e1e686-68d0-448f-8d2f-40412784058b",
   "metadata": {},
   "outputs": [],
   "source": [
    "def add_three_numbers(a, b, c):\n",
    "    traceback.print_stack()\n",
    "    return a + b + c\n",
    "\n",
    "dis.dis(add_three_numbers)"
   ]
  },
  {
   "cell_type": "markdown",
   "id": "3a985b00-5946-4176-9c2b-8f44fe1323c8",
   "metadata": {},
   "source": [
    "## If"
   ]
  },
  {
   "cell_type": "code",
   "execution_count": 12,
   "id": "303de888-fd0c-418b-b33f-2b371628e9ad",
   "metadata": {},
   "outputs": [
    {
     "name": "stdout",
     "output_type": "stream",
     "text": [
      "  2           0 LOAD_FAST                0 (x)\n",
      "              2 LOAD_CONST               1 (5)\n",
      "              4 COMPARE_OP               2 (==)\n",
      "              6 POP_JUMP_IF_FALSE        6 (to 12)\n",
      "\n",
      "  3           8 LOAD_CONST               2 (True)\n",
      "             10 RETURN_VALUE\n",
      "\n",
      "  5     >>   12 LOAD_CONST               3 (False)\n",
      "             14 RETURN_VALUE\n"
     ]
    }
   ],
   "source": [
    "def equals_five(x):\n",
    "    if x == 5:\n",
    "        return True\n",
    "    else:\n",
    "        return False\n",
    "\n",
    "dis.dis(equals_five)"
   ]
  },
  {
   "cell_type": "markdown",
   "id": "94660ee4-4400-48f1-9e88-b233ec56b527",
   "metadata": {},
   "source": [
    "## Storing and loading names"
   ]
  },
  {
   "cell_type": "code",
   "execution_count": 6,
   "id": "eafee252-d28d-46d9-af73-3a47aa5241f2",
   "metadata": {},
   "outputs": [
    {
     "name": "stdout",
     "output_type": "stream",
     "text": [
      "  2           0 LOAD_CONST               1 (0)\n",
      "              2 STORE_FAST               3 (result)\n",
      "\n",
      "  3           4 LOAD_GLOBAL              0 (range)\n",
      "              6 LOAD_FAST                0 (start)\n",
      "              8 LOAD_FAST                1 (end)\n",
      "             10 LOAD_FAST                2 (increment)\n",
      "             12 CALL_FUNCTION            3\n",
      "             14 GET_ITER\n",
      "        >>   16 FOR_ITER                 6 (to 30)\n",
      "             18 STORE_FAST               4 (item)\n",
      "\n",
      "  4          20 LOAD_FAST                3 (result)\n",
      "             22 LOAD_FAST                4 (item)\n",
      "             24 INPLACE_ADD\n",
      "             26 STORE_FAST               3 (result)\n",
      "             28 JUMP_ABSOLUTE            8 (to 16)\n",
      "\n",
      "  5     >>   30 LOAD_FAST                3 (result)\n",
      "             32 RETURN_VALUE\n"
     ]
    }
   ],
   "source": [
    "def looping_sum(start, end, increment):\n",
    "    result = 0\n",
    "    for item in range(start, end, increment):\n",
    "        result += item\n",
    "    return result\n",
    "\n",
    "dis.dis(looping_sum)"
   ]
  },
  {
   "cell_type": "code",
   "execution_count": 7,
   "id": "e0398605-d7c2-4d8b-9f73-448ef2dfb81b",
   "metadata": {},
   "outputs": [
    {
     "name": "stdout",
     "output_type": "stream",
     "text": [
      "  2           0 LOAD_CONST               0 (0)\n",
      "              2 STORE_NAME               0 (result)\n",
      "\n",
      "  3           4 LOAD_NAME                1 (range)\n",
      "              6 LOAD_NAME                2 (start)\n",
      "              8 LOAD_NAME                3 (end)\n",
      "             10 LOAD_NAME                4 (increment)\n",
      "             12 CALL_FUNCTION            3\n",
      "             14 GET_ITER\n",
      "        >>   16 FOR_ITER                 6 (to 30)\n",
      "             18 STORE_NAME               5 (item)\n",
      "\n",
      "  4          20 LOAD_NAME                0 (result)\n",
      "             22 LOAD_NAME                5 (item)\n",
      "             24 INPLACE_ADD\n",
      "             26 STORE_NAME               0 (result)\n",
      "             28 JUMP_ABSOLUTE            8 (to 16)\n",
      "\n",
      "  3     >>   30 LOAD_CONST               1 (None)\n",
      "             32 RETURN_VALUE\n"
     ]
    }
   ],
   "source": [
    "dis.dis(\n",
    "\"\"\"\n",
    "result = 0\n",
    "for item in range(start, end, increment):\n",
    "    result += item\n",
    "\"\"\"\n",
    ")"
   ]
  },
  {
   "cell_type": "code",
   "execution_count": 8,
   "id": "e88d7841-da9e-4d6d-9d6b-b1508e7cc881",
   "metadata": {},
   "outputs": [
    {
     "name": "stdout",
     "output_type": "stream",
     "text": [
      "0.2829467076808214\n"
     ]
    }
   ],
   "source": [
    "import time\n",
    "\n",
    "start = time.perf_counter()\n",
    "looping_sum(1, 10000000, 1)\n",
    "end = time.perf_counter()\n",
    "\n",
    "print(end - start)"
   ]
  },
  {
   "cell_type": "code",
   "execution_count": 9,
   "id": "f255d9e9-ce8e-4a56-83d2-e60c4ca9c01e",
   "metadata": {},
   "outputs": [
    {
     "name": "stdout",
     "output_type": "stream",
     "text": [
      "49999995000000\n",
      "0.5798297505825758\n"
     ]
    }
   ],
   "source": [
    "import time\n",
    "\n",
    "start = time.perf_counter()\n",
    "result = 0\n",
    "for item in range(1, 10000000, 1):\n",
    "    result += item\n",
    "print(result)\n",
    "end = time.perf_counter()\n",
    "\n",
    "print(end - start)"
   ]
  },
  {
   "cell_type": "code",
   "execution_count": 3,
   "id": "32803a38-4446-4583-987b-7c99dc28afbc",
   "metadata": {},
   "outputs": [
    {
     "name": "stdout",
     "output_type": "stream",
     "text": [
      "  2           0 BUILD_LIST               0\n",
      "              2 STORE_FAST               0 (x)\n",
      "\n",
      "  3           4 LOAD_GLOBAL              0 (range)\n",
      "              6 LOAD_CONST               1 (0)\n",
      "              8 LOAD_CONST               2 (10)\n",
      "             10 CALL_FUNCTION            2\n",
      "             12 GET_ITER\n",
      "        >>   14 FOR_ITER                 7 (to 30)\n",
      "             16 STORE_FAST               1 (i)\n",
      "\n",
      "  4          18 LOAD_FAST                0 (x)\n",
      "             20 LOAD_METHOD              1 (append)\n",
      "             22 LOAD_FAST                1 (i)\n",
      "             24 CALL_METHOD              1\n",
      "             26 POP_TOP\n",
      "             28 JUMP_ABSOLUTE            7 (to 14)\n",
      "\n",
      "  5     >>   30 LOAD_FAST                0 (x)\n",
      "             32 RETURN_VALUE\n"
     ]
    }
   ],
   "source": [
    "def loopy():\n",
    "    x = []\n",
    "    for i in range(0,10):\n",
    "        x.append(i)\n",
    "    return x\n",
    "\n",
    "dis.dis(loopy)"
   ]
  },
  {
   "cell_type": "code",
   "execution_count": 4,
   "id": "fecd49a0-2645-483c-91c3-229b139323e2",
   "metadata": {},
   "outputs": [
    {
     "name": "stdout",
     "output_type": "stream",
     "text": [
      "  2           0 LOAD_CONST               1 (<code object <listcomp> at 0x107699d10, file \"/var/folders/r7/7_r15vgx6n38wlfw3g8xz8t00000gn/T/ipykernel_64076/3809727906.py\", line 2>)\n",
      "              2 LOAD_CONST               2 ('compy.<locals>.<listcomp>')\n",
      "              4 MAKE_FUNCTION            0\n",
      "              6 LOAD_GLOBAL              0 (range)\n",
      "              8 LOAD_CONST               3 (0)\n",
      "             10 LOAD_CONST               4 (10)\n",
      "             12 CALL_FUNCTION            2\n",
      "             14 GET_ITER\n",
      "             16 CALL_FUNCTION            1\n",
      "             18 STORE_FAST               0 (x)\n",
      "\n",
      "  3          20 LOAD_FAST                0 (x)\n",
      "             22 RETURN_VALUE\n",
      "\n",
      "Disassembly of <code object <listcomp> at 0x107699d10, file \"/var/folders/r7/7_r15vgx6n38wlfw3g8xz8t00000gn/T/ipykernel_64076/3809727906.py\", line 2>:\n",
      "  2           0 BUILD_LIST               0\n",
      "              2 LOAD_FAST                0 (.0)\n",
      "        >>    4 FOR_ITER                 4 (to 14)\n",
      "              6 STORE_FAST               1 (i)\n",
      "              8 LOAD_FAST                1 (i)\n",
      "             10 LIST_APPEND              2\n",
      "             12 JUMP_ABSOLUTE            2 (to 4)\n",
      "        >>   14 RETURN_VALUE\n"
     ]
    }
   ],
   "source": [
    "def compy():\n",
    "    x = [i for i in range(0,10)]\n",
    "    return x\n",
    "\n",
    "dis.dis(compy)"
   ]
  },
  {
   "cell_type": "markdown",
   "id": "01892cf1-a9ed-43e6-b283-64ae1a829bf6",
   "metadata": {},
   "source": [
    "## Is, by environment"
   ]
  },
  {
   "cell_type": "code",
   "execution_count": null,
   "id": "df34e7f5-9643-4296-b284-a9aa3a21242e",
   "metadata": {},
   "outputs": [],
   "source": [
    "def notebook_is():\n",
    "    two_hundred_fifty_seven = 257\n",
    "    two_hundred_fifty_seven_again = 257\n",
    "    return two_hundred_fifty_seven is two_hundred_fifty_seven_again"
   ]
  },
  {
   "cell_type": "code",
   "execution_count": null,
   "id": "29075cd4-f701-4c2e-b7de-4231a69cbd0d",
   "metadata": {},
   "outputs": [],
   "source": [
    "notebook_is()"
   ]
  },
  {
   "cell_type": "code",
   "execution_count": null,
   "id": "3f8df36d-244b-40b1-a549-180d33304b28",
   "metadata": {},
   "outputs": [],
   "source": [
    "dis.dis(notebook_is)"
   ]
  },
  {
   "cell_type": "code",
   "execution_count": null,
   "id": "d8bfdeb0-6c29-43c4-9129-56b2611afbfe",
   "metadata": {},
   "outputs": [],
   "source": [
    "\n",
    "two_hundred_fifty_seven = 257\n",
    "two_hundred_fifty_seven_again = 257\n",
    "\n",
    "two_hundred_fifty_seven is two_hundred_fifty_seven_again\n"
   ]
  },
  {
   "cell_type": "code",
   "execution_count": null,
   "id": "7c705042-7103-45a2-bf38-93c0f1f462c5",
   "metadata": {},
   "outputs": [],
   "source": [
    "dis.dis('''\n",
    "two_hundred_fifty_seven = 257\n",
    "two_hundred_fifty_seven_again = 257\n",
    "\n",
    "two_hundred_fifty_seven is two_hundred_fifty_seven_again\n",
    "''')"
   ]
  },
  {
   "cell_type": "markdown",
   "id": "b638d74c-63e9-4927-811b-097ed2cd3966",
   "metadata": {},
   "source": [
    "## Resources:\n",
    "\n",
    " - [dis documentation](https://docs.python.org/3/library/dis.html)"
   ]
  },
  {
   "cell_type": "code",
   "execution_count": null,
   "id": "7f25e387-51ab-469b-82c7-9d406345b981",
   "metadata": {},
   "outputs": [],
   "source": []
  }
 ],
 "metadata": {
  "kernelspec": {
   "display_name": "Python 3 (ipykernel)",
   "language": "python",
   "name": "python3"
  },
  "language_info": {
   "codemirror_mode": {
    "name": "ipython",
    "version": 3
   },
   "file_extension": ".py",
   "mimetype": "text/x-python",
   "name": "python",
   "nbconvert_exporter": "python",
   "pygments_lexer": "ipython3",
   "version": "3.10.8"
  }
 },
 "nbformat": 4,
 "nbformat_minor": 5
}
